bamboo_cpp_bind.cpython-37m-x86_64-linux-gnu.so
.libsbamboo_cpp_bind/libboost_filesystem-mt-15995281.so.1.53.0
.libsbamboo_cpp_bind/libprotobuf-0afef250.so.18.0.0
.libsbamboo_cpp_bind/libarrow-da3b1b1d.so.16.0.0
.libsbamboo_cpp_bind/libboost_regex-mt-4ce74748.so.1.53.0
.libsbamboo_cpp_bind/libbz2-a273e504.so.1.0.6
.libsbamboo_cpp_bind/libboost_program_options-mt-2a5c99f5.so.1.53.0
.libsbamboo_cpp_bind/libicuuc-78e81a18.so.50.2
.libsbamboo_cpp_bind/libz-d8a329de.so.1.2.7
.libsbamboo_cpp_bind/libboost_iostreams-mt-ac4c5d52.so.1.53.0
.libsbamboo_cpp_bind/libicudata-cb3ba60c.so.50.2
.libsbamboo_cpp_bind/libboost_system-mt-3562243b.so.1.53.0
.libsbamboo_cpp_bind/libavrocpp-1717cd81.so.1.8.2.0
.libsbamboo_cpp_bind/libicui18n-c2f95ea2.so.50.2
bamboo/util.py
bamboo/core.py
bamboo/nodes.py
bamboo/__init__.py
bamboo/clusions.py
bamboo/locking_io.py
bamboo/converters/obj.py
bamboo/converters/extensions.py
bamboo/converters/__init__.py
bamboo_tests/avro_tests.py
bamboo_tests/node_tests.py
bamboo_tests/clusion_tests.py
bamboo_tests/json_tests.py
bamboo_tests/__init__.py
bamboo_tests/pbd_tests.py
bamboo_tests/arrow_tests.py
bamboo_tests/test_utils.py
bamboo_nested-0.1.0.dist-info/top_level.txt
bamboo_nested-0.1.0.dist-info/RECORD
bamboo_nested-0.1.0.dist-info/METADATA
bamboo_nested-0.1.0.dist-info/WHEEL
