Metadata-Version: 2.1
Name: bamboo-nested
Version: 0.1.0
Summary: A project for feeding various nested data formats into pandas
Home-page: https://github.com/mvilim/bamboo
Author: Michael Vilim
Author-email: michael.vilim@gmail.com
License: UNKNOWN
Platform: UNKNOWN
Requires-Dist: pandas (>=0.22.0)
Requires-Dist: numpy (>=1.15.0)
Requires-Dist: six (>=1.12.0)
Requires-Dist: enum34 (>=1.1.6) ; python_version < "3.0"
